{"imagePath":"Demon_tex_0.png","SubTexture":[{"x":2,"y":650,"width":416,"name":"1637-10","height":173},{"x":420,"y":706,"width":414,"name":"1637-11","height":173},{"x":509,"y":178,"width":419,"name":"1637-7","height":174},{"x":2,"y":475,"width":419,"name":"1637-8","height":173},{"x":423,"y":530,"width":416,"name":"1637-5","height":174},{"x":509,"y":2,"width":419,"name":"1637-6","height":174},{"x":509,"y":354,"width":417,"name":"1637-9","height":174},{"x":2,"y":825,"width":412,"name":"1637-12","height":172},{"y":530,"frameX":-6,"frameHeight":179,"height":174,"frameY":0,"frameWidth":159,"width":144,"name":"gaum01","x":841},{"x":780,"y":909,"width":188,"name":"1326-4","height":80},{"x":416,"y":881,"width":362,"name":"1326-8","height":107},{"x":928,"y":354,"width":87,"name":"yinmo10","height":142},{"x":970,"y":909,"width":42,"name":"yinmo11","height":70},{"y":706,"frameX":-8,"frameHeight":201,"height":201,"frameY":0,"frameWidth":183,"width":174,"name":"yinmoqe01","x":836},{"x":930,"y":2,"width":87,"name":"yinmo06","height":139},{"y":2,"frameX":-30,"frameHeight":471,"height":471,"frameY":0,"frameWidth":559,"width":505,"name":"heiqiu01","x":2},{"x":930,"y":271,"width":76,"name":"yinmo07-3","height":64},{"x":930,"y":143,"width":84,"name":"yinmo07","height":126},{"x":423,"y":475,"width":60,"name":"yinmo07-1","height":50},{"y":981,"frameX":-9,"frameHeight":51,"height":28,"frameY":-14,"frameWidth":48,"width":26,"name":"huomiao01","x":970}],"name":"Demon"}